logicbit/__init__.py
logicbit/__main__.py
logicbit/clock.py
logicbit/keyboard.py
logicbit/logic.py
logicbit/quine_mccluskey.py
logicbit/utils.py
logicbit-1.2.8.dist-info/LICENSE
logicbit-1.2.8.dist-info/METADATA
logicbit-1.2.8.dist-info/WHEEL
logicbit-1.2.8.dist-info/top_level.txt
logicbit-1.2.8.dist-info/RECORD
