Metadata-Version: 2.1
Name: logicbit
Version: 1.2.8
Summary: logicbit is a library for digital logic simulation
Home-page: https://github.com/clnrp/logicbit
Author: Cleoner Pietralonga
Author-email: cleonerp@gmail.com
License: UNKNOWN
Platform: UNKNOWN
Classifier: Development Status :: 4 - Beta
Classifier: Intended Audience :: Developers
Classifier: Topic :: Software Development :: Build Tools
Classifier: License :: OSI Approved :: Apache Software License
Classifier: Programming Language :: Python :: 2.7
Classifier: Programming Language :: Python :: 3
Classifier: Programming Language :: Python :: 3.4
Classifier: Programming Language :: Python :: 3.5
Requires-Dist: numpy
